[
  {
    "epoch": 0,
    "accuracy": {
      "retain": 96.57037037112389,
      "forget": 32.955555555555556,
      "val": 84.56000004882813,
      "test": 90.63333333333334
    },
    "skip_rate": 0.0,
    "duration": 106.43999600410461
  },
  {
    "epoch": 1,
    "accuracy": {
      "retain": 97.58518518066407,
      "forget": 0.5111111111111111,
      "val": 82.1000000366211,
      "test": 91.63333333333334
    },
    "skip_rate": 0.0,
    "duration": 97.46372079849243
  },
  {
    "epoch": 2,
    "accuracy": {
      "retain": 96.78765431722005,
      "forget": 0.0,
      "val": 81.78000004882813,
      "test": 90.66666666666667
    },
    "skip_rate": 0.0,
    "duration": 97.38818049430847
  },
  {
    "epoch": 3,
    "accuracy": {
      "retain": 95.45432098840784,
      "forget": 0.0,
      "val": 81.05999986572266,
      "test": 89.37777777777778
    },
    "skip_rate": 0.0,
    "duration": 96.74046421051025
  },
  {
    "epoch": 4,
    "accuracy": {
      "retain": 95.66913579870153,
      "forget": 0.0,
      "val": 80.63999995117187,
      "test": 90.34444444444445
    },
    "skip_rate": 0.0,
    "duration": 89.47217988967896
  },
  {
    "epoch": 5,
    "accuracy": {
      "retain": 97.61975308641975,
      "forget": 0.0,
      "val": 82.9799999633789,
      "test": 91.23333333333333
    },
    "skip_rate": 0.0,
    "duration": 87.67187285423279
  },
  {
    "epoch": 6,
    "accuracy": {
      "retain": 97.14074073621961,
      "forget": 0.0,
      "val": 82.13999989013672,
      "test": 91.27777777777777
    },
    "skip_rate": 0.0,
    "duration": 88.44921231269836
  },
  {
    "epoch": 7,
    "accuracy": {
      "retain": 94.75061728470413,
      "forget": 0.0,
      "val": 79.87999998779297,
      "test": 88.83333333333333
    },
    "skip_rate": 0.0,
    "duration": 87.0536630153656
  },
  {
    "epoch": 8,
    "accuracy": {
      "retain": 97.63209876091098,
      "forget": 0.0,
      "val": 82.83999985351562,
      "test": 91.35555555555555
    },
    "skip_rate": 0.0,
    "duration": 88.40786862373352
  },
  {
    "epoch": 9,
    "accuracy": {
      "retain": 97.20246913580247,
      "forget": 0.0,
      "val": 82.3199999633789,
      "test": 91.08888888888889
    },
    "skip_rate": 0.0,
    "duration": 98.6720380783081
  },
  {
    "epoch": 10,
    "accuracy": {
      "retain": 96.92592592592592,
      "forget": 0.0,
      "val": 82.07999986572266,
      "test": 90.8
    },
    "skip_rate": 0.0,
    "duration": 90.38948464393616
  },
  {
    "epoch": 11,
    "accuracy": {
      "retain": 97.66172839129413,
      "forget": 0.0,
      "val": 82.89999993896484,
      "test": 91.71111111111111
    },
    "skip_rate": 0.0,
    "duration": 88.57390713691711
  },
  {
    "epoch": 12,
    "accuracy": {
      "retain": 97.1259259214048,
      "forget": 0.0,
      "val": 82.21999985351563,
      "test": 90.63333333333334
    },
    "skip_rate": 0.0,
    "duration": 87.08069682121277
  },
  {
    "epoch": 13,
    "accuracy": {
      "retain": 97.64938271152826,
      "forget": 0.0,
      "val": 82.22000003662109,
      "test": 91.08888888888889
    },
    "skip_rate": 0.0,
    "duration": 88.51292943954468
  },
  {
    "epoch": 14,
    "accuracy": {
      "retain": 96.33086419376326,
      "forget": 0.0,
      "val": 81.36000003662109,
      "test": 90.3
    },
    "skip_rate": 0.0,
    "duration": 91.88945007324219
  },
  {
    "epoch": 15,
    "accuracy": {
      "retain": 97.07901234191141,
      "forget": 0.0,
      "val": 82.51999996337891,
      "test": 91.14444444444445
    },
    "skip_rate": 0.0,
    "duration": 99.0537223815918
  },
  {
    "epoch": 16,
    "accuracy": {
      "retain": 96.12098765055339,
      "forget": 0.0,
      "val": 81.05999985351562,
      "test": 89.74444444444444
    },
    "skip_rate": 0.0,
    "duration": 95.6150815486908
  },
  {
    "epoch": 17,
    "accuracy": {
      "retain": 96.77777777325666,
      "forget": 0.0,
      "val": 81.97999998779297,
      "test": 91.08888888888889
    },
    "skip_rate": 0.0,
    "duration": 87.16530275344849
  },
  {
    "epoch": 18,
    "accuracy": {
      "retain": 97.02962962962962,
      "forget": 0.0,
      "val": 82.63999985351562,
      "test": 90.61111111111111
    },
    "skip_rate": 0.0,
    "duration": 88.87782740592957
  },
  {
    "epoch": 19,
    "accuracy": {
      "retain": 96.9185185139974,
      "forget": 0.0,
      "val": 82.17999997558594,
      "test": 90.71111111111111
    },
    "skip_rate": 0.0,
    "duration": 86.01476645469666
  },
  {
    "epoch": 20,
    "accuracy": {
      "retain": 97.25432098840784,
      "forget": 0.0,
      "val": 82.65999997558593,
      "test": 90.77777777777777
    },
    "skip_rate": 0.0,
    "duration": 86.07885885238647
  },
  {
    "epoch": 21,
    "accuracy": {
      "retain": 97.80987653868875,
      "forget": 0.0,
      "val": 82.67999985351562,
      "test": 91.34444444444445
    },
    "skip_rate": 0.0,
    "duration": 87.81798267364502
  },
  {
    "epoch": 22,
    "accuracy": {
      "retain": 96.97037036584925,
      "forget": 0.0,
      "val": 81.84000003662109,
      "test": 90.46666666666667
    },
    "skip_rate": 0.0,
    "duration": 109.34697914123535
  },
  {
    "epoch": 23,
    "accuracy": {
      "retain": 96.65679012421032,
      "forget": 0.0,
      "val": 82.09999985351563,
      "test": 90.46666666666667
    },
    "skip_rate": 0.0,
    "duration": 86.70301413536072
  },
  {
    "epoch": 24,
    "accuracy": {
      "retain": 97.45925925473814,
      "forget": 0.0,
      "val": 82.20000003662109,
      "test": 90.88888888888889
    },
    "skip_rate": 0.0,
    "duration": 89.2765121459961
  },
  {
    "epoch": 25,
    "accuracy": {
      "retain": 94.61728394609617,
      "forget": 0.0,
      "val": 79.85999993896485,
      "test": 88.24444444444444
    },
    "skip_rate": 0.0,
    "duration": 83.24325180053711
  },
  {
    "epoch": 26,
    "accuracy": {
      "retain": 97.56296295844184,
      "forget": 0.0,
      "val": 82.95999991455078,
      "test": 91.03333333333333
    },
    "skip_rate": 0.0,
    "duration": 88.24709749221802
  },
  {
    "epoch": 27,
    "accuracy": {
      "retain": 97.65185185260538,
      "forget": 0.0,
      "val": 82.51999987792969,
      "test": 92.04444444444445
    },
    "skip_rate": 0.0,
    "duration": 90.4979920387268
  },
  {
    "epoch": 28,
    "accuracy": {
      "retain": 97.0469135757258,
      "forget": 0.0,
      "val": 81.9599999633789,
      "test": 90.62222222222222
    },
    "skip_rate": 0.0,
    "duration": 98.04783797264099
  },
  {
    "epoch": 29,
    "accuracy": {
      "retain": 96.98765431722005,
      "forget": 0.0,
      "val": 82.05999987792968,
      "test": 90.63333333333334
    },
    "skip_rate": 0.0,
    "duration": 91.0223879814148
  }
]